<?xml version="1.0" encoding="utf-8"?>
<LanguageData>
  <!--The following translations were generated by https://www.deepl.com/-->
  <!-- EN: Light EVA Gear -->
  <Apparel_Light_ETMG_SOS.label>轻型 EVA 装备</Apparel_Light_ETMG_SOS.label>
  <!-- EN: Offers some protection but its main purpose is to propel the user with the build in thrusters. -->
  <Apparel_Light_ETMG_SOS.description>提供一些保护，但其主要目的是利用内置推进器推动用户。</Apparel_Light_ETMG_SOS.description>
  <!-- EN: Light EVA helmet -->
  <Apparel_Light_Spacehelmet_SOS.label>轻型 EVA 头盔</Apparel_Light_Spacehelmet_SOS.label>
  <!-- EN: A helmet which protects against the vacuum of space, it doesnt offer much protection. -->
  <Apparel_Light_Spacehelmet_SOS.description>太空头盔可以抵御真空环境，但保护作用不大。</Apparel_Light_Spacehelmet_SOS.description>
  <!-- EN: civilian space undersuit -->
  <Apparel_SpaceJumpsuit_SOS.label>民用太空内衣</Apparel_SpaceJumpsuit_SOS.label>
  <!-- EN: A tight suit that protects the body from the coldness of space. Its durable and protects against energy based attacks and extreme temperatures, but is otherwise quite unimpressive. -->
  <Apparel_SpaceJumpsuit_SOS.description>一件可以保护身体免受太空寒冷侵袭的紧身衣。它经久耐用，可抵御能量攻击和极端温度，但在其他方面并不出众。</Apparel_SpaceJumpsuit_SOS.description>
  <!-- EN: military space undersuit -->
  <Apparel_SpaceJumpsuitMilitary_SOS.label>军用太空内衣</Apparel_SpaceJumpsuitMilitary_SOS.label>
  <!-- EN: The military version of the standart civilian space undersuit, the Hyperweave woven into its thicker fabric increases its protection. -->
  <Apparel_SpaceJumpsuitMilitary_SOS.description>军用版的标准民用太空内衣，在其加厚面料中编织的超编织物增强了其防护性。</Apparel_SpaceJumpsuitMilitary_SOS.description>
</LanguageData>
